logicsponge/py.typed
logicsponge/core/__init__.py
logicsponge/core/dashboard.py
logicsponge/core/datastructures.py
logicsponge/core/logicsponge.py
logicsponge/core/plot.py
logicsponge/core/source.py
logicsponge/core/stats.py
logicsponge/core/assets/custom-script.js
logicsponge/core/assets/dagre-d3.js
logicsponge/core/assets/typography.css
logicsponge_core-0.0.17.dist-info/METADATA
logicsponge_core-0.0.17.dist-info/WHEEL
logicsponge_core-0.0.17.dist-info/licenses/LICENSE
logicsponge_core-0.0.17.dist-info/RECORD
