Metadata-Version: 2.3
Name: logicsponge-core
Version: 0.0.17
Summary: A real-time data processing pipeline
Project-URL: Repository, https://github.com/innatelogic/logicsponge-core.git
Author-email: Benedikt Bollig <bollig@lmf.cnrs.fr>, Matthias Függer <mfuegger@lmf.cnrs.fr>, Thomas Nowak <thomas@thomasnowak.net>
Maintainer-email: Benedikt Bollig <bollig@lmf.cnrs.fr>, Matthias Függer <mfuegger@lmf.cnrs.fr>, Thomas Nowak <thomas@thomasnowak.net>
License:                                  Apache License
License-File: LICENSE
Keywords: data processing,real-time,time series
Classifier: Development Status :: 4 - Beta
Classifier: Programming Language :: Python
Requires-Python: >=3.11
Requires-Dist: chardet
Requires-Dist: dash
Requires-Dist: dash-bootstrap-components
Requires-Dist: dash-svg
Requires-Dist: frozendict
Requires-Dist: gdown
Requires-Dist: matplotlib
Requires-Dist: numpy
Requires-Dist: plotly
Requires-Dist: readerwriterlock
Requires-Dist: scipy
Requires-Dist: watchdog
Requires-Dist: zodb
